environment_mlflow_client/__init__.py
environment_mlflow_client/env_mlflow_client.py
environment_mlflow_client-3.0.2.dist-info/LICENSE.txt
environment_mlflow_client-3.0.2.dist-info/METADATA
environment_mlflow_client-3.0.2.dist-info/WHEEL
environment_mlflow_client-3.0.2.dist-info/RECORD
