Metadata-Version: 2.1
Name: environment-mlflow-client
Version: 3.0.2
Summary: environment scoped mlflow client
Home-page: https://github.com/nederlandsespoorwegen/environment_mlflow_client
License: LICENSE.txt
Author: Team Sigma
Author-email: team.sigma@ns.nl
Requires-Python: >=3.10,<4.0
Classifier: License :: Other/Proprietary License
Classifier: Programming Language :: Python :: 3
Classifier: Programming Language :: Python :: 3.10
Classifier: Programming Language :: Python :: 3.11
Classifier: Programming Language :: Python :: 3.12
Requires-Dist: mlflow (>=2.1.0,<3.0.0)
